{
  "avg": {
    "116": [
      "1020.0"
    ], 
    "124": [
      "135.8"
    ], 
    "151": [
      "560.0"
    ], 
    "168": [
      "508.0"
    ], 
    "176": [
      "102.0"
    ], 
    "178": [
      "503.0"
    ], 
    "197": [
      "510.0"
    ], 
    "202": [
      "506.0"
    ], 
    "214": [
      "545.0"
    ], 
    "252": [
      "534.0"
    ], 
    "286": [
      "504.0"
    ], 
    "396": [
      "562.0"
    ], 
    "639": [
      "523.0"
    ], 
    "770": [
      "250199.0"
    ], 
    "799": [
      "556.0"
    ], 
    "803": [
      "555.0"
    ], 
    "1296": [
      "250199.17"
    ]
  }, 
  "workflows": {
    "102.0": [
      176
    ], 
    "1020.0": [
      116
    ], 
    "135.8": [
      124
    ], 
    "250199.0": [
      770
    ], 
    "250199.17": [
      1296
    ], 
    "503.0": [
      178
    ], 
    "504.0": [
      286
    ], 
    "506.0": [
      202
    ], 
    "508.0": [
      168
    ], 
    "510.0": [
      197
    ], 
    "523.0": [
      639
    ], 
    "534.0": [
      252
    ], 
    "545.0": [
      214
    ], 
    "555.0": [
      803
    ], 
    "556.0": [
      799
    ], 
    "560.0": [
      151
    ], 
    "562.0": [
      396
    ]
  }
}
